commod/__init__.py
commod/arc.py
commod-0.0.1.dist-info/LICENSE
commod-0.0.1.dist-info/METADATA
commod-0.0.1.dist-info/WHEEL
commod-0.0.1.dist-info/top_level.txt
commod-0.0.1.dist-info/RECORD
