Metadata-Version: 2.1
Name: commod
Version: 0.0.1
Summary: A library for building arcs
Author-email: Artin Sarraf <sarraf.artin@gmail.com>
Project-URL: Homepage, https://github.com/aa1371/commod
Project-URL: Bug Tracker, https://github.com/aa1371/commod/issues
Classifier: Programming Language :: Python :: 3
Classifier: License :: OSI Approved :: MIT License
Classifier: Operating System :: OS Independent
Requires-Python: >=3.7
License-File: LICENSE
